{
  "expo": {
    "name": "MatrixTransposeApp",
    "slug": "MatrixTransposeApp",
    "version": "1.0.0",
    "orientation": "portrait",
    "icon": "./assets/logo3.png",
    "userInterfaceStyle": "light",
    "splash": {
      "image": "./assets/",
      "resizeMode": "contain",
      "backgroundColor": "#ffffff"
    },
    "assetBundlePatterns": [
      "**/*"
    ],
    "ios": {
      "supportsTablet": true
    },
    "android": {
      "adaptiveIcon": {
        "foregroundImage": "./assets/adaptive-icon.png",
        "backgroundColor": "#ffffff"
      }
    },
    "web": {
      "favicon": "./assets/favicon.png"
    }
  }
}
